Metadata-Version: 2.1
Name: kwcache
Version: 0.0.2
Summary: Package for function caching
Author: Sidq
Author-email: abba.dmytro@gmail.com
License:                                  Apache License
Project-URL: GitHub, https://github.com/sidqdev/kwcache
Project-URL: Telegram, https://t.me/sidqdev
Classifier: Programming Language :: Python :: 3
Classifier: Operating System :: OS Independent
Requires-Python: >=3.6
License-File: LICENSE
